qrev_instructor/__init__.py
qrev_instructor/apis.py
qrev_instructor/client.py
qrev_instructor/maybe.py
qrev_instructor/models.py
qrev_instructor/py.typed
qrev_instructor/utils.py
qrev_instructor-0.5.8.dist-info/METADATA
qrev_instructor-0.5.8.dist-info/WHEEL
qrev_instructor-0.5.8.dist-info/RECORD
