Metadata-Version: 2.1
Name: qrev-instructor
Version: 0.5.8
Summary: 
Author: leeparnell
Author-email: 152523161+leeparnell@users.noreply.github.com
Requires-Python: >=3.11,<4.0
Classifier: Programming Language :: Python :: 3
Classifier: Programming Language :: Python :: 3.11
Classifier: Programming Language :: Python :: 3.12
Requires-Dist: anthropic (>=0.31.0)
Requires-Dist: instructor (>=1.3.2,<2.0.0)
Requires-Dist: pydantic-settings (>=2.3.4,<3.0.0)
